airflow/providers/celery/__init__.py
airflow/providers/celery/get_provider_info.py
airflow/providers/celery/version_compat.py
airflow/providers/celery/cli/__init__.py
airflow/providers/celery/cli/celery_command.py
airflow/providers/celery/cli/definition.py
airflow/providers/celery/executors/__init__.py
airflow/providers/celery/executors/celery_executor.py
airflow/providers/celery/executors/celery_executor_utils.py
airflow/providers/celery/executors/celery_kubernetes_executor.py
airflow/providers/celery/executors/default_celery.py
airflow/providers/celery/sensors/__init__.py
airflow/providers/celery/sensors/celery_queue.py
apache_airflow_providers_celery-3.15.1.dist-info/entry_points.txt
apache_airflow_providers_celery-3.15.1.dist-info/licenses/LICENSE
apache_airflow_providers_celery-3.15.1.dist-info/licenses/NOTICE
apache_airflow_providers_celery-3.15.1.dist-info/WHEEL
apache_airflow_providers_celery-3.15.1.dist-info/METADATA
apache_airflow_providers_celery-3.15.1.dist-info/RECORD
